stopwatch/__init__.py
stopwatch_timer-1.0.2.dist-info/LICENSE
stopwatch_timer-1.0.2.dist-info/METADATA
stopwatch_timer-1.0.2.dist-info/WHEEL
stopwatch_timer-1.0.2.dist-info/top_level.txt
stopwatch_timer-1.0.2.dist-info/RECORD
