Metadata-Version: 2.1
Name: stopwatch-timer
Version: 1.0.2
Summary: A stopwatch class that can be used as a timer.
Home-page: UNKNOWN
Author: Benjamin Richter
License: UNKNOWN
Platform: UNKNOWN
Classifier: Development Status :: 5 - Production/Stable
Classifier: License :: OSI Approved :: MIT License
Classifier: Natural Language :: English
Classifier: Operating System :: OS Independent
Classifier: Programming Language :: Python :: 3
Requires-Python: >=3
